immunopepper/__init__.py
immunopepper/constant.py
immunopepper/immuno_filter.py
immunopepper/immuno_model.py
immunopepper/immuno_mutation.py
immunopepper/immuno_nametuple.py
immunopepper/immuno_preprocess.py
immunopepper/immunopepper_build.py
immunopepper/immunopepper_diff.py
immunopepper/immunopepper_filter.py
immunopepper/immunopepper_makebg.py
immunopepper/io_utils.py
immunopepper/main_immuno.py
immunopepper/utils.py
immunopepper-1.1.0.dist-info/AUTHORS
immunopepper-1.1.0.dist-info/LICENSE
immunopepper-1.1.0.dist-info/METADATA
immunopepper-1.1.0.dist-info/WHEEL
immunopepper-1.1.0.dist-info/entry_points.txt
immunopepper-1.1.0.dist-info/top_level.txt
immunopepper-1.1.0.dist-info/RECORD
