Metadata-Version: 2.1
Name: immunopepper
Version: 1.1.0
Summary: Software to translate splicing graphs into peptides
Home-page: https://github.com/ratschlab/immunopepper
Author: Andre Kahles
Author-email: andre.kahles@inf.ethz.ch
License: MIT license
Keywords: immunopepper
Platform: UNKNOWN
Classifier: Development Status :: 2 - Pre-Alpha
Classifier: Intended Audience :: Developers
Classifier: License :: OSI Approved :: MIT License
Classifier: Natural Language :: English
Classifier: Programming Language :: Python :: 2
Classifier: Programming Language :: Python :: 2.7
Classifier: Programming Language :: Python :: 3
Classifier: Programming Language :: Python :: 3.4
Classifier: Programming Language :: Python :: 3.5
Classifier: Programming Language :: Python :: 3.6
Requires-Dist: h5py (==2.8.0)
Requires-Dist: numpy (>=1.13)
Requires-Dist: psutil (==5.4.6)
Requires-Dist: scipy (==1.1.0)
Requires-Dist: biopython
Requires-Dist: spladder (==2.2.2)
